cryptologging/__init__.py
cryptologging/algorithms/__init__.py
cryptologging/algorithms/abstract.py
cryptologging/algorithms/hash.py
cryptologging/formatter.py
cryptologging/utils.py
cryptologging-1.0.0.dist-info/WHEEL
cryptologging-1.0.0.dist-info/METADATA
cryptologging-1.0.0.dist-info/RECORD
