Metadata-Version: 2.1
Name: cryptologging
Version: 1.0.0
Summary: Log encryption
Author: Cheldaev Alexey
Author-email: alexothers35@gmail.com
Requires-Python: >=3.9,<4.0
Classifier: Programming Language :: Python :: 3
Classifier: Programming Language :: Python :: 3.10
Classifier: Programming Language :: Python :: 3.9
Requires-Dist: orjson (>=3.8.0,<4.0.0)
